setup.py
event_bus/__init__.py
event_bus/abstract/__init__.py
event_bus/abstract/rabbit.py
event_bus/bus/__init__.py
event_bus/bus/event_bus.py
event_bus/fanout/__init__.py
event_bus/fanout/fanout_queue.py
event_bus/test/__init__.py
event_bus/test/tests.py
invento_iot_event_bus.egg-info/PKG-INFO
invento_iot_event_bus.egg-info/SOURCES.txt
invento_iot_event_bus.egg-info/dependency_links.txt
invento_iot_event_bus.egg-info/not-zip-safe
invento_iot_event_bus.egg-info/requires.txt
invento_iot_event_bus.egg-info/top_level.txt