Metadata-Version: 1.0
Name: invento-iot-event-bus
Version: 1.0.1.7
Summary: Iot invento mqtt event bus
Home-page: https://github.com/jakekutsel/invento-event-bus
Author: Jake Kutsel
Author-email: e.kutel@invento.by
License: MIT
Platform: UNKNOWN
